README.md
setup.py
FabGameOfLife/GameOfLife.py
FabGameOfLife/__init__.py
FabGameOfLife_p.egg-info/PKG-INFO
FabGameOfLife_p.egg-info/SOURCES.txt
FabGameOfLife_p.egg-info/dependency_links.txt
FabGameOfLife_p.egg-info/top_level.txt