Metadata-Version: 1.0
Name: FabGameOfLife-p
Version: 1.1
Summary: Game of Life implementation with many options. 
Home-page: https://github.com/FapCarbonator/GameOfLifePython/archive/1.tar.gz
Author: Fabio
Author-email: fabiomelis@hotmail.nl
License: UNKNOWN
Platform: UNKNOWN
